MANIFEST.in
requirements.txt
setup.py
webmuxd
webmux/__init__.py
webmux/auth.py
webmux/connection.py
webmux/handlers.py
webmux/main.py
webmux/models.py
webmux/protocols.py
webmux/pubsub.py
webmux/session.py
webmux/sftp.py
webmux/ssh.py
webmux/terminal.py
webmux/user.py
webmux/web_terminal.py
webmux.egg-info/PKG-INFO
webmux.egg-info/SOURCES.txt
webmux.egg-info/dependency_links.txt
webmux.egg-info/requires.txt
webmux.egg-info/top_level.txt
webmux/static/css/style.css
webmux/static/css/bootstrap/bootstrap-theme.css
webmux/static/css/bootstrap/bootstrap-theme.css.map
webmux/static/css/bootstrap/bootstrap-theme.min.css
webmux/static/css/bootstrap/bootstrap.css
webmux/static/css/bootstrap/bootstrap.css.map
webmux/static/css/bootstrap/bootstrap.min.css
webmux/static/css/fonts/glyphicons-halflings-regular.eot
webmux/static/css/fonts/glyphicons-halflings-regular.svg
webmux/static/css/fonts/glyphicons-halflings-regular.ttf
webmux/static/css/fonts/glyphicons-halflings-regular.woff
webmux/static/css/fonts/source-code-pro/LICENSE.txt
webmux/static/css/fonts/source-code-pro/source-code-pro.css
webmux/static/css/fonts/source-code-pro/eot/SourceCodePro-Black.eot
webmux/static/css/fonts/source-code-pro/eot/SourceCodePro-Bold.eot
webmux/static/css/fonts/source-code-pro/eot/SourceCodePro-ExtraLight.eot
webmux/static/css/fonts/source-code-pro/eot/SourceCodePro-Light.eot
webmux/static/css/fonts/source-code-pro/eot/SourceCodePro-Medium.eot
webmux/static/css/fonts/source-code-pro/eot/SourceCodePro-Regular.eot
webmux/static/css/fonts/source-code-pro/eot/SourceCodePro-Semibold.eot
webmux/static/css/fonts/source-code-pro/svg/SourceCodePro-Black.svg
webmux/static/css/fonts/source-code-pro/svg/SourceCodePro-Bold.svg
webmux/static/css/fonts/source-code-pro/svg/SourceCodePro-ExtraLight.svg
webmux/static/css/fonts/source-code-pro/svg/SourceCodePro-Light.svg
webmux/static/css/fonts/source-code-pro/svg/SourceCodePro-Medium.svg
webmux/static/css/fonts/source-code-pro/svg/SourceCodePro-Regular.svg
webmux/static/css/fonts/source-code-pro/svg/SourceCodePro-Semibold.svg
webmux/static/css/fonts/source-code-pro/woff/otf/SourceCodePro-Black.otf.woff
