Metadata-Version: 1.0
Name: webmux
Version: 0.1.11
Summary: An open-source web based SSH terminal multiplexer
Home-page: http://github.com/ronreiter/webmux
Author: Ron Reiter (@ronreiter)
Author-email: ron.reiter@gmail.com
License: MIT
Platform: UNKNOWN
